{
  "contacts": [
    {
      "firstName": "Theunis Jr",
      "lastName": "Knötze",
      "blockContact": false,
      "addressId": 4,
      "id": 4,
      "address": {
        "street": "Dunno",
        "city": "Dunno",
        "postCode": "Somewhere",
        "id": 4
      }
    },
    {
      "firstName": "Seeb",
      "lastName": "KnowsItAll",
      "blockContact": false,
      "addressId": 13,
      "id": 5
    }
  ],
  "addresses": [
    {
      "id": 1,
      "street": "10 Downing Street",
      "city": "London",
      "postCode": "SW1A 2AB"
    },
    {
      "id": 2,
      "street": "Buckingham Palace",
      "city": "London",
      "postCode": "SW1A 1AA"
    },
    {
      "street": "Buckingham Palace",
      "city": "London",
      "postCode": "SW1A 1AA",
      "id": 3
    },
    {
      "street": "Dunno",
      "city": "Dunno",
      "postCode": "Somewhere",
      "id": 4
    },
    {
      "street": "Hell Road",
      "city": "Hell",
      "postCode": "666",
      "id": 5
    },
    {
      "street": "fdsfsd",
      "city": "sdfsdf",
      "postCode": "dsfsdfds",
      "id": 6
    },
    {
      "street": "hhh",
      "city": "hh",
      "postCode": "hhh",
      "id": 7
    },
    {
      "street": "rtkjrtk",
      "city": "yktuy",
      "postCode": "kytkyt",
      "id": 8
    },
    {
      "street": "rtkjrtk",
      "city": "yktuy",
      "postCode": "kytkyt",
      "id": 9
    },
    {
      "street": "gggggggg",
      "city": "erh",
      "postCode": "erhsss",
      "id": 10
    },
    {
      "street": "ffff",
      "city": "fgggg",
      "postCode": "fgfg",
      "id": 11
    },
    {
      "street": "dfhfhf",
      "city": "dhdfhdh",
      "postCode": "dfhf",
      "id": 12
    },
    {
      "street": "hell",
      "city": "yeah",
      "postCode": "101",
      "id": 13
    },
    {
      "street": "",
      "city": "",
      "postCode": "",
      "id": 14
    },
    {
      "street": "",
      "city": "",
      "postCode": "",
      "id": 15
    },
    {
      "street": "g",
      "city": "",
      "postCode": "",
      "id": 16
    }
  ]
}